qupepfold/__init__.py
qupepfold/cli.py
qupepfold/qupepfold.py
qupepfold-0.6.1.data/scripts/qupepfold
qupepfold-0.6.1.dist-info/METADATA
qupepfold-0.6.1.dist-info/WHEEL
qupepfold-0.6.1.dist-info/top_level.txt
qupepfold-0.6.1.dist-info/RECORD
